{
 "periodNum": 6,
 "vehicles": [
  {
   "id": 0,
   "capacity": 1570
  }
 ],
 "nodes": [
  {
   "id": 0,
   "x": 453,
   "y": 380,
   "initQuantity": 2460,
   "capacity": 8742,
   "minLevel": 0,
   "unitDemand": -1047,
   "holidingCost": 0.03
  },
  {
   "id": 1,
   "x": 67,
   "y": 232,
   "initQuantity": 36,
   "capacity": 54,
   "minLevel": 0,
   "unitDemand": 18,
   "holidingCost": 0.02
  },
  {
   "id": 2,
   "x": 30,
   "y": 379,
   "initQuantity": 66,
   "capacity": 132,
   "minLevel": 0,
   "unitDemand": 66,
   "holidingCost": 0.02
  },
  {
   "id": 3,
   "x": 453,
   "y": 322,
   "initQuantity": 134,
   "capacity": 201,
   "minLevel": 0,
   "unitDemand": 67,
   "holidingCost": 0.02
  },
  {
   "id": 4,
   "x": 132,
   "y": 314,
   "initQuantity": 63,
   "capacity": 126,
   "minLevel": 0,
   "unitDemand": 63,
   "holidingCost": 0.02
  },
  {
   "id": 5,
   "x": 194,
   "y": 455,
   "initQuantity": 96,
   "capacity": 144,
   "minLevel": 0,
   "unitDemand": 48,
   "holidingCost": 0.04
  },
  {
   "id": 6,
   "x": 454,
   "y": 474,
   "initQuantity": 39,
   "capacity": 78,
   "minLevel": 0,
   "unitDemand": 39,
   "holidingCost": 0.05
  },
  {
   "id": 7,
   "x": 228,
   "y": 14,
   "initQuantity": 64,
   "capacity": 96,
   "minLevel": 0,
   "unitDemand": 32,
   "holidingCost": 0.02
  },
  {
   "id": 8,
   "x": 329,
   "y": 182,
   "initQuantity": 13,
   "capacity": 26,
   "minLevel": 0,
   "unitDemand": 13,
   "holidingCost": 0.02
  },
  {
   "id": 9,
   "x": 54,
   "y": 41,
   "initQuantity": 57,
   "capacity": 114,
   "minLevel": 0,
   "unitDemand": 57,
   "holidingCost": 0.03
  },
  {
   "id": 10,
   "x": 255,
   "y": 276,
   "initQuantity": 68,
   "capacity": 136,
   "minLevel": 0,
   "unitDemand": 68,
   "holidingCost": 0.02
  },
  {
   "id": 11,
   "x": 498,
   "y": 94,
   "initQuantity": 85,
   "capacity": 170,
   "minLevel": 0,
   "unitDemand": 85,
   "holidingCost": 0.04
  },
  {
   "id": 12,
   "x": 185,
   "y": 288,
   "initQuantity": 106,
   "capacity": 159,
   "minLevel": 0,
   "unitDemand": 53,
   "holidingCost": 0.02
  },
  {
   "id": 13,
   "x": 330,
   "y": 319,
   "initQuantity": 69,
   "capacity": 138,
   "minLevel": 0,
   "unitDemand": 69,
   "holidingCost": 0.03
  },
  {
   "id": 14,
   "x": 230,
   "y": 1,
   "initQuantity": 79,
   "capacity": 158,
   "minLevel": 0,
   "unitDemand": 79,
   "holidingCost": 0.02
  },
  {
   "id": 15,
   "x": 453,
   "y": 230,
   "initQuantity": 65,
   "capacity": 130,
   "minLevel": 0,
   "unitDemand": 65,
   "holidingCost": 0.02
  },
  {
   "id": 16,
   "x": 184,
   "y": 404,
   "initQuantity": 54,
   "capacity": 108,
   "minLevel": 0,
   "unitDemand": 54,
   "holidingCost": 0.04
  },
  {
   "id": 17,
   "x": 211,
   "y": 56,
   "initQuantity": 148,
   "capacity": 222,
   "minLevel": 0,
   "unitDemand": 74,
   "holidingCost": 0.02
  },
  {
   "id": 18,
   "x": 93,
   "y": 7,
   "initQuantity": 106,
   "capacity": 159,
   "minLevel": 0,
   "unitDemand": 53,
   "holidingCost": 0.02
  },
  {
   "id": 19,
   "x": 90,
   "y": 317,
   "initQuantity": 42,
   "capacity": 63,
   "minLevel": 0,
   "unitDemand": 21,
   "holidingCost": 0.04
  },
  {
   "id": 20,
   "x": 325,
   "y": 269,
   "initQuantity": 23,
   "capacity": 46,
   "minLevel": 0,
   "unitDemand": 23,
   "holidingCost": 0.04
  }
 ],
 "bestObj": 7309.54,
 "referenceObj": 7394.84,
 "referenceTime": 508
}
